{
  "category": "demonstration",
  "subcategory": "modelagem",
  "colors": [
    "preto"
  ],
  "features": [
    "não enrola",
    "empina bumbum",
    "modela cintura",
    "super confortável"
  ],
  "context": "promoção e destaque de funcionalidades",
  "confidence": 0.95,
  "tags": [
    "frete grátis",
    "50% off",
    "promoção",
    "conforto",
    "modelagem"
  ],
  "description": "Imagem demonstrando a calcinha modeladora preta com foco em modelagem e conforto, destacando frete grátis e desconto de 50%.",
  "recommendedFor": [
    "promoções",
    "destaque de funcionalidades"
  ]
}